odoo8_addon_attachments_to_filesystem-8.0.1.0.1-py2.7-nspkg.pth
odoo8_addon_attachments_to_filesystem-8.0.1.0.1.dist-info/DESCRIPTION.rst
odoo8_addon_attachments_to_filesystem-8.0.1.0.1.dist-info/METADATA
odoo8_addon_attachments_to_filesystem-8.0.1.0.1.dist-info/RECORD
odoo8_addon_attachments_to_filesystem-8.0.1.0.1.dist-info/WHEEL
odoo8_addon_attachments_to_filesystem-8.0.1.0.1.dist-info/metadata.json
odoo8_addon_attachments_to_filesystem-8.0.1.0.1.dist-info/namespace_packages.txt
odoo8_addon_attachments_to_filesystem-8.0.1.0.1.dist-info/top_level.txt
odoo_addons/attachments_to_filesystem/README.rst
odoo_addons/attachments_to_filesystem/__init__.py
odoo_addons/attachments_to_filesystem/__openerp__.py
odoo_addons/attachments_to_filesystem/data/init.xml
odoo_addons/attachments_to_filesystem/data/ir_cron.xml
odoo_addons/attachments_to_filesystem/models/__init__.py
odoo_addons/attachments_to_filesystem/models/ir_attachment.py
odoo_addons/attachments_to_filesystem/static/description/icon.png
